README.md
setup.cfg
setup.py
Frank_distributions.egg-info/PKG-INFO
Frank_distributions.egg-info/SOURCES.txt
Frank_distributions.egg-info/dependency_links.txt
Frank_distributions.egg-info/not-zip-safe
Frank_distributions.egg-info/top_level.txt
distributions/Binomialdistribution.py
distributions/Gaussiandistribution.py
distributions/Generaldistribution.py
distributions/__init__.py