Metadata-Version: 1.0
Name: Frank-distributions
Version: 2.7
Summary: Gaussian and Binomial distributions
Home-page: UNKNOWN
Author: Frank
Author-email: UNKNOWN
License: UNKNOWN
Platform: UNKNOWN
